streaming_stats.py
streaming_stats-0.3.dist-info/LICENSE
streaming_stats-0.3.dist-info/METADATA
streaming_stats-0.3.dist-info/WHEEL
streaming_stats-0.3.dist-info/top_level.txt
streaming_stats-0.3.dist-info/RECORD
