Metadata-Version: 2.1
Name: streaming-stats
Version: 0.3
Summary: Statistics calculator of a series in O(1) space complexity
Home-page: https://github.com/ed21b006/RunningStats
Author: Aditya Raj
Author-email: adityaraj867604@gmail.com
License: MIT
Platform: UNKNOWN
Classifier: License :: OSI Approved :: MIT License
Classifier: Programming Language :: Python :: 3
Classifier: Programming Language :: Python :: 3.8
License-File: LICENSE
